{
  "matchningslista": {
    "antal_platsannonser": 9,
    "antal_platsannonser_exakta": 9,
    "antal_platsannonser_narliggande": 0,
    "antal_platserTotal": 16,
    "antal_sidor": 1,
    "matchningdata": [
      {
        "annonsid": "6516393",
        "annonsrubrik": "Webbkommunikatör sökes till Diös , Östersund",
        "yrkesbenamning": "Webmaster",
        "arbetsplatsnamn": "Diös Fastigheter AB",
        "kommunnamn": "Östersund",
        "kommunkod": 2380,
        "publiceraddatum": "2015-12-23T11:16:00+01:00",
        "annonsurl": "http://www.arbetsformedlingen.se/ledigajobb?id=6516393",
        "relevans": 100,
        "antalplatser": "1",
        "antalPlatserVisa": 1
      },
      {
        "annonsid": "2844507",
        "annonsrubrik": "Technical Specialists till Östersund",
        "yrkesbenamning": "IT-tekniker/Datatekniker",
        "arbetsplatsnamn": "Tieto Sweden AB",
        "kommunnamn": "Östersund",
        "kommunkod": 2380,
        "publiceraddatum": "2015-12-22T12:53:00+01:00",
        "annonsurl": "http://www.arbetsformedlingen.se/ledigajobb?id=2844507",
        "relevans": 100,
        "antalplatser": "1",
        "antalPlatserVisa": 1
      },
      {
        "annonsid": "6512221",
        "annonsrubrik": "Rekrytering av senior supporttekniker till Medius Ascendo",
        "yrkesbenamning": "Systemadministratör",
        "arbetsplatsnamn": "StudentConsulting",
        "kommunnamn": "Östersund",
        "kommunkod": 2380,
        "publiceraddatum": "2015-12-21T12:00:00+01:00",
        "annonsurl": "http://www.arbetsformedlingen.se/ledigajobb?id=6512221",
        "relevans": 100,
        "antalplatser": "2",
        "antalPlatserVisa": 1
      },
      {
        "annonsid": "2842947",
        "annonsrubrik": "Tekniker / IT / support / 2nd line",
        "yrkesbenamning": "Helpdesktekniker/Supporttekniker",
        "arbetsplatsnamn": "Centric Professionals AB",
        "kommunnamn": "Östersund",
        "kommunkod": 2380,
        "publiceraddatum": "2015-12-18T16:36:00+01:00",
        "annonsurl": "http://www.arbetsformedlingen.se/ledigajobb?id=2842947",
        "relevans": 100,
        "antalplatser": "5",
        "antalPlatserVisa": 1
      },
      {
        "annonsid": "6505407",
        "annonsrubrik": "Projektledare IT - infrastruktur",
        "yrkesbenamning": "IT-strateg",
        "arbetsplatsnamn": "Region Jämtland Härjedalen",
        "kommunnamn": "Östersund",
        "kommunkod": 2380,
        "publiceraddatum": "2015-12-15T15:30:00+01:00",
        "annonsurl": "http://www.arbetsformedlingen.se/ledigajobb?id=6505407",
        "relevans": 100,
        "antalplatser": "1",
        "antalPlatserVisa": 1
      },
      {
        "annonsid": "6505307",
        "annonsrubrik": "Utvecklare / projektledare beslutsstöd",
        "yrkesbenamning": "IT-strateg",
        "arbetsplatsnamn": "Region Jämtland Härjedalen",
        "kommunnamn": "Östersund",
        "kommunkod": 2380,
        "publiceraddatum": "2015-12-15T14:50:00+01:00",
        "annonsurl": "http://www.arbetsformedlingen.se/ledigajobb?id=6505307",
        "relevans": 100,
        "antalplatser": "1",
        "antalPlatserVisa": 1
      },
      {
        "annonsid": "2839507",
        "annonsrubrik": "Vi söker IT - tjänsteansvarig till IT - avdelningen",
        "yrkesbenamning": "IT-samordnare",
        "arbetsplatsnamn": "Statens servicecenter Östersund",
        "kommunnamn": "Östersund",
        "kommunkod": 2380,
        "publiceraddatum": "2015-12-14T00:00:00+01:00",
        "annonsurl": "http://www.arbetsformedlingen.se/ledigajobb?id=2839507",
        "relevans": 100,
        "antalplatser": "1",
        "antalPlatserVisa": 1
      },
      {
        "annonsid": "6484636",
        "annonsrubrik": "Helpdeskmedarbetare till stort IT - tjänsteföretag",
        "yrkesbenamning": "Helpdesktekniker/Supporttekniker",
        "arbetsplatsnamn": "Academic Work",
        "kommunnamn": "Östersund",
        "kommunkod": 2380,
        "publiceraddatum": "2015-11-28T00:00:00+01:00",
        "annonsurl": "http://www.arbetsformedlingen.se/ledigajobb?id=6484636",
        "relevans": 100,
        "antalplatser": "1",
        "antalPlatserVisa": 1
      },
      {
        "annonsid": "2778933",
        "annonsrubrik": "IT - jobb / 1st line support / Fujitsu i Östersund",
        "yrkesbenamning": "Helpdesktekniker/Supporttekniker",
        "arbetsplatsnamn": "Centric Professionals AB",
        "kommunnamn": "Östersund",
        "kommunkod": 2380,
        "publiceraddatum": "2015-09-17T00:00:00+02:00",
        "annonsurl": "http://www.arbetsformedlingen.se/ledigajobb?id=2778933",
        "relevans": 100,
        "antalplatser": "3",
        "antalPlatserVisa": 1
      }
    ]
  }
}
